README.md
setup.cfg
setup.py
src/xdocx/__init__.py
src/xdocx/docx_util.py
src/xdocx/gen_report.py
src/xdocx/main.py
src/xdocx/template_data.py
src/xdocx.egg-info/PKG-INFO
src/xdocx.egg-info/SOURCES.txt
src/xdocx.egg-info/dependency_links.txt
src/xdocx.egg-info/entry_points.txt
src/xdocx.egg-info/top_level.txt